omnibus/settings.py
omnibus/exceptions.py
omnibus/pubsub.py
omnibus/authenticators.py
omnibus/__init__.py
omnibus/factories.py
omnibus/compat.py
omnibus/connection.py
omnibus/context_processors.py
omnibus/api.py
omnibus/static/omnibus/omnibus.min.js
omnibus/static/omnibus/sockjs.js
omnibus/static/omnibus/sockjs.min.js
omnibus/static/omnibus/json2.min.js
omnibus/static/omnibus/omnibus.js
omnibus/static/omnibus/json2.js
omnibus/management/__init__.py
omnibus/management/commands/omnibusd.py
omnibus/management/commands/__init__.py
django_omnibus-0.2.0.dist-info/metadata.json
django_omnibus-0.2.0.dist-info/DESCRIPTION.rst
django_omnibus-0.2.0.dist-info/METADATA
django_omnibus-0.2.0.dist-info/top_level.txt
django_omnibus-0.2.0.dist-info/WHEEL
django_omnibus-0.2.0.dist-info/RECORD
